deeperwin/__init__.py
deeperwin/__main__.py
deeperwin/ase_bindings.py
deeperwin/available_gpus.py
deeperwin/bfgs.py
deeperwin/configuration.py
deeperwin/dispatch.py
deeperwin/evaluation.py
deeperwin/hamiltonian.py
deeperwin/kfac.py
deeperwin/loggers.py
deeperwin/main.py
deeperwin/mcmc.py
deeperwin/model.py
deeperwin/optimization.py
deeperwin/orbitals.py
deeperwin/process_molecule.py
deeperwin/process_molecules_shared.py
deeperwin/register_curvature.py
deeperwin/sweep_agent.py
deeperwin/utils.py
deeperwin/wandb_utils.py
deeperwin/kfac_ferminet_alpha/__init__.py
deeperwin/kfac_ferminet_alpha/curvature_blocks.py
deeperwin/kfac_ferminet_alpha/distributions.py
deeperwin/kfac_ferminet_alpha/estimator.py
deeperwin/kfac_ferminet_alpha/example.py
deeperwin/kfac_ferminet_alpha/layers_and_loss_tags.py
deeperwin/kfac_ferminet_alpha/loss_functions.py
deeperwin/kfac_ferminet_alpha/optimizer.py
deeperwin/kfac_ferminet_alpha/setup.py
deeperwin/kfac_ferminet_alpha/tag_graph_matcher.py
deeperwin/kfac_ferminet_alpha/tracer.py
deeperwin/kfac_ferminet_alpha/utils.py
deeperwin/kfac_ferminet_alpha/tests/__init__.py
deeperwin/kfac_ferminet_alpha/tests/common.py
deeperwin/kfac_ferminet_alpha/tests/graph_matcher_test.py
deeperwin/kfac_ferminet_alpha/tests/tracer_test.py
deeperwin-1.1.0.dist-info/LICENSE
deeperwin-1.1.0.dist-info/METADATA
deeperwin-1.1.0.dist-info/WHEEL
deeperwin-1.1.0.dist-info/entry_points.txt
deeperwin-1.1.0.dist-info/top_level.txt
deeperwin-1.1.0.dist-info/RECORD
