Metadata-Version: 2.1
Name: deeperwin
Version: 1.1.0
Summary: A JAX based framework to calculate deep-learning VMC solutions to the Schrödinger equation
Home-page: UNKNOWN
Author: Michael Scherbela, Leon Gerard, Rafael Reisenhofer
Author-email: deeperwin.datascience@univie.ac.at
License: UNKNOWN
Platform: UNKNOWN
Classifier: Programming Language :: Python :: 3
Classifier: License :: OSI Approved :: MIT License
Classifier: Operating System :: OS Independent
Requires-Python: >=3.8
Requires-Dist: jax
Requires-Dist: jaxlib
Requires-Dist: pyscf
Requires-Dist: h5py (==3.2.1)
Requires-Dist: ruamel.yaml
Requires-Dist: pydantic
Requires-Dist: matplotlib
Requires-Dist: pandas
Requires-Dist: parse
Requires-Dist: networkx
Requires-Dist: ordered-set
Requires-Dist: wandb
Provides-Extra: full
Requires-Dist: sphinx ; extra == 'full'
Requires-Dist: sphinx-rtd-theme ; extra == 'full'
Requires-Dist: pytest ; extra == 'full'
